stix_shifter_modules/splunk/__init__.py
stix_shifter_modules/splunk/entry_point.py
stix_shifter_modules/splunk/configuration/config.json
stix_shifter_modules/splunk/configuration/dialects.json
stix_shifter_modules/splunk/configuration/lang_en.json
stix_shifter_modules/splunk/stix_translation/__init__.py
stix_shifter_modules/splunk/stix_translation/car_query_translator.py
stix_shifter_modules/splunk/stix_translation/encoders.py
stix_shifter_modules/splunk/stix_translation/json_to_stix_translator.py
stix_shifter_modules/splunk/stix_translation/object_scopers.py
stix_shifter_modules/splunk/stix_translation/query_constructor.py
stix_shifter_modules/splunk/stix_translation/query_translator.py
stix_shifter_modules/splunk/stix_translation/splunk_utils.py
stix_shifter_modules/splunk/stix_translation/transformers.py
stix_shifter_modules/splunk/stix_translation/json/from_stix_map.json
stix_shifter_modules/splunk/stix_translation/json/operators.json
stix_shifter_modules/splunk/stix_translation/json/select_fields.json
stix_shifter_modules/splunk/stix_translation/json/to_stix_map.json
stix_shifter_modules/splunk/stix_translation/json/stix_2_1/from_stix_map.json
stix_shifter_modules/splunk/stix_translation/json/stix_2_1/to_stix_map.json
stix_shifter_modules/splunk/stix_transmission/__init__.py
stix_shifter_modules/splunk/stix_transmission/api_client.py
stix_shifter_modules/splunk/stix_transmission/auth.py
stix_shifter_modules/splunk/stix_transmission/delete_connector.py
stix_shifter_modules/splunk/stix_transmission/error_mapper.py
stix_shifter_modules/splunk/stix_transmission/ping_connector.py
stix_shifter_modules/splunk/stix_transmission/query_connector.py
stix_shifter_modules/splunk/stix_transmission/results_connector.py
stix_shifter_modules/splunk/stix_transmission/status_connector.py
stix_shifter_modules_splunk-8.0.2.dist-info/licenses/AUTHORS.md
stix_shifter_modules_splunk-8.0.2.dist-info/licenses/LICENSE.md
stix_shifter_modules_splunk-8.0.2.dist-info/licenses/NOTICE
stix_shifter_modules_splunk-8.0.2.dist-info/METADATA
stix_shifter_modules_splunk-8.0.2.dist-info/WHEEL
stix_shifter_modules_splunk-8.0.2.dist-info/top_level.txt
stix_shifter_modules_splunk-8.0.2.dist-info/RECORD
